etc/kernelconfig/default
kernelconfig/__init__.py
kernelconfig/kernel.py
kernelconfig/main.py
kernelconfig/settings.py
kernelconfig-0.3.4.data/data/share/doc/kernelconfig-0.3.4/README.html
kernelconfig-0.3.4.data/data/share/kernelconfig/sources/arch
kernelconfig-0.3.4.data/data/share/kernelconfig/sources/liquorix
kernelconfig-0.3.4.data/data/share/kernelconfig/sources/ubuntu
kernelconfig-0.3.4.dist-info/LICENSE.txt
kernelconfig-0.3.4.dist-info/METADATA
kernelconfig-0.3.4.dist-info/WHEEL
kernelconfig-0.3.4.dist-info/entry_points.txt
kernelconfig-0.3.4.dist-info/top_level.txt
kernelconfig-0.3.4.dist-info/RECORD
