Metadata-Version: 2.1
Name: kernelconfig
Version: 0.3.4
Summary: Generate custom Linux kernel configurations from curated sources
Home-page: https://github.com/Calchan/kernelconfig
Author: Denis Dupeyron
Author-email: calchan@gentoo.org
License: GPLv3
Keywords: Linux kernel configuration
Platform: UNKNOWN
Classifier: Development Status :: 3 - Alpha
Classifier: Environment :: Console
Classifier: Intended Audience :: System Administrators
Classifier: License :: OSI Approved :: GNU General Public License v3 (GPLv3)
Classifier: Natural Language :: English
Classifier: Operating System :: POSIX :: Linux
Classifier: Programming Language :: Python :: 3.4
Classifier: Topic :: System :: Installation/Setup
Classifier: Topic :: System :: Operating System Kernels :: Linux
